django_db_translate/__init__.py
django_db_translate/apps.py
django_db_translate/middleware.py
django_db_translate/models.py
django_db_translate/admin/__init__.py
django_db_translate/admin/admin.py
django_db_translate/admin/forms.py
django_db_translate/admin/views.py
django_db_translate/management/commands/makemessages.py
django_db_translate/migrations/0001_initial.py
django_db_translate/migrations/0002_alter_dbtranslatepermissions_options.py
django_db_translate/migrations/__init__.py
django_db_translate/templates/db_translate/locale.html
django_db_translate/translations/__init__.py
django_db_translate/translations/loader.py
django_db_translate/translations/query.py
django_db_translate-0.3.0.dist-info/licenses/LICENSE
django_db_translate-0.3.0.dist-info/METADATA
django_db_translate-0.3.0.dist-info/WHEEL
django_db_translate-0.3.0.dist-info/top_level.txt
django_db_translate-0.3.0.dist-info/RECORD
