Metadata-Version: 2.4
Name: django-db-translate
Version: 0.3.0
Summary: A Django app with utilites to assist in project-wide translation
Author-email: Mason Weaver <mason@swingproxy.com>
License-Expression: BSD-3-Clause
Project-URL: Homepage, https://github.com/Otach/django-db-translate
Classifier: Framework :: Django
Classifier: Framework :: Django :: 6.0
Classifier: Intended Audience :: Developers
Classifier: Operating System :: OS Independent
Classifier: Programming Language :: Python
Classifier: Programming Language :: Python :: 3
Classifier: Programming Language :: Python :: 3 :: Only
Classifier: Topic :: Internet :: WWW/HTTP
Classifier: Topic :: Internet :: WWW/HTTP :: Dynamic Content
Requires-Python: >=3.12
License-File: LICENSE
Requires-Dist: django>=6.0
Requires-Dist: polib>=1.2.0
Dynamic: license-file
